{
  "resourceType": "Device",
  "id": "device-1234",
  "meta": {
    "profile": [
      "http://t-cabs.org/StructureDefinition/t-cabs-device-beatmungsgeraet"
    ]
  },
  "identifier": [
    {
      "system": "http://www.loewenstein_example.com/identifiers/devices",
      "value": "1234"
    }
  ],
  "deviceName": [
    {
      "type": "model-name",
      "name": "prisma SOFT"
    }
  ],
  "version": [
    {
      "value": "v1.2.3"
    }
  ],
  "owner": {
    "display": "Löwenstein"
  },
  "status": "active",
  "serialNumber": "ABC5678DE",
  "patient": {
    "reference": "Patient/patient-123456"
  },
  "manufacturer": "Löwenstein Medical"
}
